{
  "quotes": {
    "sp500": {
      "price": 7102.86,
      "previousClose": 6845.5,
      "marketState": "UNKNOWN",
      "fiftyTwoWeekHigh": 7147.78,
      "fiftyTwoWeekLow": 5371.96,
      "ytdLow": 6316.91,
      "drawdownAtLow": -11.62,
      "drawdownCurrent": -0.63,
      "gainFromLow": 12.44,
      "gainToATH": 0.63
    },
    "ndx": {
      "price": 26749.12,
      "previousClose": 25249.85,
      "marketState": "UNKNOWN",
      "fiftyTwoWeekHigh": 27007.87,
      "fiftyTwoWeekLow": 18744.47,
      "ytdLow": 22841.42,
      "drawdownAtLow": -15.43,
      "drawdownCurrent": -0.96,
      "gainFromLow": 17.11,
      "gainToATH": 0.97
    },
    "ixic": {
      "price": 24413.02,
      "previousClose": 23241.99,
      "marketState": "UNKNOWN",
      "fiftyTwoWeekHigh": 24664.87,
      "fiftyTwoWeekLow": 16744.97,
      "ytdLow": 20690.25,
      "drawdownAtLow": -16.11,
      "drawdownCurrent": -1.02,
      "gainFromLow": 17.99,
      "gainToATH": 1.03
    }
  },
  "timestamp": "2026-04-23T19:52:59.761021+00:00"
}