{
  "quotes": {
    "sp500": {
      "price": 7473.41,
      "previousClose": 6845.5,
      "marketState": "UNKNOWN",
      "fiftyTwoWeekHigh": 7620.9,
      "fiftyTwoWeekLow": 5943.23,
      "ytdLow": 6316.91,
      "drawdownAtLow": -17.11,
      "drawdownCurrent": -1.94,
      "gainFromLow": 18.31,
      "gainToATH": 1.97
    },
    "ndx": {
      "price": 30260.43,
      "previousClose": 25249.85,
      "marketState": "UNKNOWN",
      "fiftyTwoWeekHigh": 30762.2,
      "fiftyTwoWeekLow": 21532.32,
      "ytdLow": 22841.42,
      "drawdownAtLow": -25.75,
      "drawdownCurrent": -1.63,
      "gainFromLow": 32.48,
      "gainToATH": 1.66
    },
    "ixic": {
      "price": 26194.65,
      "previousClose": 23241.99,
      "marketState": "UNKNOWN",
      "fiftyTwoWeekHigh": 27190.21,
      "fiftyTwoWeekLow": 19334.98,
      "ytdLow": 20690.25,
      "drawdownAtLow": -23.91,
      "drawdownCurrent": -3.66,
      "gainFromLow": 26.6,
      "gainToATH": 3.8
    }
  },
  "timestamp": "2026-06-22T16:25:21.122652+00:00"
}